{
  "filterEmpty": true,
  "excludePaths": [],
  "fileFilter": "",
  "useIncludeTags": false,
  "taskIncludeTags": [],
  "fileIncludeTags": [],
  "useExcludeTags": false,
  "taskExcludeTags": [],
  "fileExcludeTags": [],
  "styles": [
    "style1"
  ],
  "dailyNoteFolder": "02 Diary/day",
  "dailyNoteFormat": "YYYYMMDD",
  "sectionForNewTasks": "## 日志",
  "hideTags": [],
  "forward": true,
  "sort": "(t) => t.order",
  "taskStatusOrder": [
    "overdue",
    "due",
    "scheduled",
    "start",
    "process",
    "unplanned",
    "done",
    "cancelled"
  ],
  "dateFormat": "YYYYMMDD",
  "inbox": "Inbox.md",
  "taskFiles": [],
  "tagColorPalette": {
    "#TODO": "#339988",
    "#TEST": "#998877"
  },
  "useCounters": true,
  "useQuickEntry": true,
  "useYearHeader": true,
  "useRelative": true,
  "useRecurrence": true,
  "usePriority": true,
  "useTags": true,
  "useFileBadge": true,
  "useSection": true,
  "useCompletedTasks": true,
  "defaultTodayFocus": true,
  "defaultFilters": ""
}